[
  {
    "cname": "杭州",
    "suggest_places": [
      {
        "cname": "西湖",
        "url": "/sight/hangzhou14/49894.html"
      },
      {
        "cname": "灵隐寺",
        "url": "/sight/hangzhou14/2040.html"
      },
      {
        "cname": "雷峰塔",
        "url": "/sight/hangzhou14/2033.html"
      },
      {
        "cname": "西溪湿地公园（东区）",
        "url": "/sight/hangzhou14/25481.html"
      },
      {
        "cname": "苏堤",
        "url": "/sight/hangzhou14/2036.html"
      }
    ],
    "url": "/sightlist/hangzhou14.html"
  },
  {
    "cname": "嘉兴",
    "suggest_places": [
      {
        "cname": "乌镇",
        "url": "/sight/jiaxing272/16170.html"
      },
      {
        "cname": "西塘风景区",
        "url": "/sight/jiaxing272/17884.html"
      },
      {
        "cname": "南湖景区",
        "url": "/sight/jiaxing272/141755.html"
      },
      {
        "cname": "盐官观潮景区",
        "url": "/sight/jiaxing272/61335.html"
      },
      {
        "cname": "嘉兴",
        "url": "/sight/jiaxing272/139810.html"
      }
    ],
    "url": "/sightlist/jiaxing272.html"
  },
  {
    "cname": "宁波",
    "suggest_places": [
      {
        "cname": "天一阁博物馆",
        "url": "/sight/ningbo83/9964.html"
      },
      {
        "cname": "天一广场",
        "url": "/sight/ningbo83/20509.html"
      },
      {
        "cname": "东钱湖",
        "url": "/sight/ningbo83/16825.html"
      },
      {
        "cname": "溪口风景区",
        "url": "/sight/ningbo83/135869.html"
      },
      {
        "cname": "老外滩",
        "url": "/sight/ningbo83/48549.html"
      }
    ],
    "url": "/sightlist/ningbo83.html"
  },
  {
    "cname": "西塘",
    "suggest_places": [
      {
        "cname": "西塘风景区",
        "url": "/sight/xitang15/17884.html"
      },
      {
        "cname": "烟雨长廊",
        "url": "/sight/xitang15/2094.html"
      },
      {
        "cname": "送子来凤桥",
        "url": "/sight/xitang15/2098.html"
      },
      {
        "cname": "石皮弄",
        "url": "/sight/xitang15/2100.html"
      },
      {
        "cname": "环秀桥",
        "url": "/sight/xitang15/7128.html"
      }
    ],
    "url": "/sightlist/xitang15.html"
  },
  {
    "cname": "乌镇",
    "suggest_places": [
      {
        "cname": "乌镇",
        "url": "/sight/wuzhen508/16170.html"
      },
      {
        "cname": "西栅",
        "url": "/sight/wuzhen508/139898.html"
      },
      {
        "cname": "东栅",
        "url": "/sight/wuzhen508/139826.html"
      },
      {
        "cname": "西栅夜游",
        "url": "/sight/wuzhen508/135954.html"
      },
      {
        "cname": "茅盾故居",
        "url": "/sight/wuzhen508/18054.html"
      }
    ],
    "url": "/sightlist/wuzhen508.html"
  },
  {
    "cname": "绍兴",
    "suggest_places": [
      {
        "cname": "鲁迅故里景区",
        "url": "/sight/shaoxing18/2193.html"
      },
      {
        "cname": "沈园",
        "url": "/sight/shaoxing18/2204.html"
      },
      {
        "cname": "兰亭",
        "url": "/sight/shaoxing18/2190.html"
      },
      {
        "cname": "东湖",
        "url": "/sight/shaoxing18/2206.html"
      },
      {
        "cname": "绍兴柯岩风景区",
        "url": "/sight/shaoxing18/2189.html"
      }
    ],
    "url": "/sightlist/shaoxing18.html"
  },
  {
    "cname": "普陀山",
    "suggest_places": [
      {
        "cname": "普陀山风景区",
        "url": "/sight/putuoshan16/126016.html"
      },
      {
        "cname": "法雨寺",
        "url": "/sight/putuoshan16/2131.html"
      },
      {
        "cname": "紫竹林",
        "url": "/sight/putuoshan16/2129.html"
      },
      {
        "cname": "慧济寺",
        "url": "/sight/putuoshan16/2132.html"
      },
      {
        "cname": "千步沙",
        "url": "/sight/putuoshan16/2134.html"
      }
    ],
    "url": "/sightlist/putuoshan16.html"
  },
  {
    "cname": "临安",
    "suggest_places": [
      {
        "cname": "浙西大峡谷",
        "url": "/sight/linan88/51377.html"
      },
      {
        "cname": "大明山风景区",
        "url": "/sight/linan88/4140.html"
      },
      {
        "cname": "飞来峰",
        "url": "/sight/linan88/134627.html"
      },
      {
        "cname": "太湖源",
        "url": "/sight/linan88/4137.html"
      },
      {
        "cname": "天目山景区",
        "url": "/sight/linan88/74700.html"
      }
    ],
    "url": "/sightlist/linan88.html"
  },
  {
    "cname": "千岛湖",
    "suggest_places": [
      {
        "cname": "千岛湖景区",
        "url": "/sight/qiandaohu17/135831.html"
      },
      {
        "cname": "千岛湖森林氧吧",
        "url": "/sight/qiandaohu17/52366.html"
      },
      {
        "cname": "千岛湖东南湖区景区",
        "url": "/sight/qiandaohu17/135833.html"
      },
      {
        "cname": "梅峰岛",
        "url": "/sight/qiandaohu17/16656.html"
      },
      {
        "cname": "石林景区",
        "url": "/sight/qiandaohu17/135915.html"
      }
    ],
    "url": "/sightlist/qiandaohu17.html"
  },
  {
    "cname": "温州",
    "suggest_places": [
      {
        "cname": "石桅岩",
        "url": "/sight/wenzhou153/3900.html"
      },
      {
        "cname": "江心屿",
        "url": "/sight/wenzhou153/16188.html"
      },
      {
        "cname": "望海楼",
        "url": "/sight/wenzhou153/67355.html"
      },
      {
        "cname": "楠溪江风景旅游区",
        "url": "/sight/wenzhou153/56450.html"
      },
      {
        "cname": "崖下库",
        "url": "/sight/wenzhou153/3897.html"
      }
    ],
    "url": "/sightlist/wenzhou153.html"
  },
  {
    "cname": "嵊泗",
    "suggest_places": [
      {
        "cname": "基湖沙滩",
        "url": "/sight/shengsi82/4037.html"
      },
      {
        "cname": "枸杞岛",
        "url": "/sight/shengsi82/56063.html"
      },
      {
        "cname": "六井潭",
        "url": "/sight/shengsi82/21750.html"
      },
      {
        "cname": "大悲山",
        "url": "/sight/shengsi82/21749.html"
      },
      {
        "cname": "南长涂沙滩",
        "url": "/sight/shengsi82/4019.html"
      }
    ],
    "url": "/sightlist/shengsi82.html"
  },
  {
    "cname": "湖州",
    "suggest_places": [
      {
        "cname": "南浔古镇",
        "url": "/sight/huzhou68/135811.html"
      },
      {
        "cname": "莫干山景区",
        "url": "/sight/huzhou68/135799.html"
      },
      {
        "cname": "藏龙百瀑",
        "url": "/sight/huzhou68/55781.html"
      },
      {
        "cname": "小莲庄",
        "url": "/sight/huzhou68/3980.html"
      },
      {
        "cname": "安吉竹博园",
        "url": "/sight/huzhou68/55782.html"
      }
    ],
    "url": "/sightlist/huzhou68.html"
  },
  {
    "cname": "舟山",
    "suggest_places": [
      {
        "cname": "普陀山风景区",
        "url": "/sight/zhoushan479/126016.html"
      },
      {
        "cname": "法雨寺",
        "url": "/sight/zhoushan479/2131.html"
      },
      {
        "cname": "紫竹林",
        "url": "/sight/zhoushan479/2129.html"
      },
      {
        "cname": "慧济寺",
        "url": "/sight/zhoushan479/2132.html"
      },
      {
        "cname": "朱家尖风景区",
        "url": "/sight/zhoushan479/139887.html"
      }
    ],
    "url": "/sightlist/zhoushan479.html"
  },
  {
    "cname": "丽水",
    "suggest_places": [
      {
        "cname": "南尖岩景区",
        "url": "/sight/lishui441/74075.html"
      },
      {
        "cname": "遂昌金矿国家矿山公园",
        "url": "/sight/lishui441/56269.html"
      },
      {
        "cname": "神龙谷",
        "url": "/sight/lishui441/74211.html"
      },
      {
        "cname": "古堰画乡景区",
        "url": "/sight/lishui441/56153.html"
      },
      {
        "cname": "云和梯田景区",
        "url": "/sight/lishui441/135977.html"
      }
    ],
    "url": "/sightlist/lishui441.html"
  },
  {
    "cname": "金华",
    "suggest_places": [
      {
        "cname": "横店影视城",
        "url": "/sight/jinhua219/75555.html"
      },
      {
        "cname": "诸葛八卦村",
        "url": "/sight/jinhua219/72172.html"
      },
      {
        "cname": "秦王宫景区",
        "url": "/sight/jinhua219/74877.html"
      },
      {
        "cname": "梦幻谷景区",
        "url": "/sight/jinhua219/75559.html"
      },
      {
        "cname": "双龙洞景区",
        "url": "/sight/jinhua219/8605.html"
      }
    ],
    "url": "/sightlist/jinhua219.html"
  },
  {
    "cname": "台州",
    "suggest_places": [
      {
        "cname": "神仙居",
        "url": "/sight/taizhou402/16209.html"
      },
      {
        "cname": "江南长城",
        "url": "/sight/taizhou402/16913.html"
      },
      {
        "cname": "长屿硐天",
        "url": "/sight/taizhou402/16920.html"
      },
      {
        "cname": "琼台仙谷",
        "url": "/sight/taizhou402/9079.html"
      },
      {
        "cname": "台州海洋世界",
        "url": "/sight/taizhou402/62844.html"
      }
    ],
    "url": "/sightlist/taizhou402.html"
  },
  {
    "cname": "雁荡山",
    "suggest_places": [
      {
        "cname": "雁荡山",
        "url": "/sight/yandangshan217/135800.html"
      },
      {
        "cname": "大龙湫景区",
        "url": "/sight/yandangshan217/8418.html"
      },
      {
        "cname": "灵岩景区",
        "url": "/sight/yandangshan217/61650.html"
      },
      {
        "cname": "小龙湫",
        "url": "/sight/yandangshan217/8404.html"
      },
      {
        "cname": "灵峰景区",
        "url": "/sight/yandangshan217/61623.html"
      }
    ],
    "url": "/sightlist/yandangshan217.html"
  },
  {
    "cname": "衢州",
    "suggest_places": [
      {
        "cname": "廿八都",
        "url": "/sight/quzhou174/16771.html"
      },
      {
        "cname": "江郎山景区",
        "url": "/sight/quzhou174/16223.html"
      },
      {
        "cname": "龙游石窟",
        "url": "/sight/quzhou174/16766.html"
      },
      {
        "cname": "根宫佛国文化旅游区",
        "url": "/sight/quzhou174/143278.html"
      },
      {
        "cname": "天脊龙门",
        "url": "/sight/quzhou174/135859.html"
      }
    ],
    "url": "/sightlist/quzhou174.html"
  },
  {
    "cname": "朱家尖",
    "suggest_places": [
      {
        "cname": "朱家尖风景区",
        "url": "/sight/zhujiajian256/139887.html"
      },
      {
        "cname": "南沙",
        "url": "/sight/zhujiajian256/10297.html"
      },
      {
        "cname": "大青山",
        "url": "/sight/zhujiajian256/10316.html"
      },
      {
        "cname": "乌石塘",
        "url": "/sight/zhujiajian256/135865.html"
      },
      {
        "cname": "东沙",
        "url": "/sight/zhujiajian256/126053.html"
      }
    ],
    "url": "/sightlist/zhujiajian256.html"
  },
  {
    "cname": "象山",
    "suggest_places": [
      {
        "cname": "象山影视城",
        "url": "/sight/xiangshan723/65051.html"
      },
      {
        "cname": "石浦渔港古城",
        "url": "/sight/xiangshan723/65045.html"
      },
      {
        "cname": "中国渔村",
        "url": "/sight/xiangshan723/65054.html"
      },
      {
        "cname": "松兰山海滨度假区",
        "url": "/sight/xiangshan723/65049.html"
      },
      {
        "cname": "花岙岛",
        "url": "/sight/xiangshan723/65098.html"
      }
    ],
    "url": "/sightlist/xiangshan723.html"
  },
  {
    "cname": "安吉",
    "suggest_places": [
      {
        "cname": "藏龙百瀑",
        "url": "/sight/anji686/55781.html"
      },
      {
        "cname": "安吉竹博园",
        "url": "/sight/anji686/55782.html"
      },
      {
        "cname": "中南百草原",
        "url": "/sight/anji686/125988.html"
      },
      {
        "cname": "浙北大峡谷",
        "url": "/sight/anji686/135807.html"
      },
      {
        "cname": "中国大竹海",
        "url": "/sight/anji686/135810.html"
      }
    ],
    "url": "/sightlist/anji686.html"
  },
  {
    "cname": "溪口",
    "suggest_places": [
      {
        "cname": "溪口风景区",
        "url": "/sight/xikou69/135869.html"
      },
      {
        "cname": "雪窦山",
        "url": "/sight/xikou69/107387.html"
      },
      {
        "cname": "雪窦寺",
        "url": "/sight/xikou69/4025.html"
      },
      {
        "cname": "三隐潭",
        "url": "/sight/xikou69/66245.html"
      },
      {
        "cname": "滕头生态旅游区",
        "url": "/sight/xikou69/135857.html"
      }
    ],
    "url": "/sightlist/xikou69.html"
  },
  {
    "cname": "武义",
    "suggest_places": [
      {
        "cname": "清水湾沁温泉",
        "url": "/sight/wuyi1004/135782.html"
      },
      {
        "cname": "郭洞",
        "url": "/sight/wuyi1004/49018.html"
      },
      {
        "cname": "牛头山国家森林公园",
        "url": "/sight/wuyi1004/125954.html"
      },
      {
        "cname": "唐风露天温泉",
        "url": "/sight/wuyi1004/135855.html"
      },
      {
        "cname": "寿仙谷",
        "url": "/sight/wuyi1004/56039.html"
      }
    ],
    "url": "/sightlist/wuyi1004.html"
  },
  {
    "cname": "海宁",
    "suggest_places": [
      {
        "cname": "盐官观潮景区",
        "url": "/sight/haining86/61335.html"
      },
      {
        "cname": "海宁潮",
        "url": "/sight/haining86/4737.html"
      },
      {
        "cname": "观潮胜地公园",
        "url": "/sight/haining86/61302.html"
      },
      {
        "cname": "徐志摩故居",
        "url": "/sight/haining86/61317.html"
      },
      {
        "cname": "海神庙",
        "url": "/sight/haining86/3948.html"
      }
    ],
    "url": "/sightlist/haining86.html"
  },
  {
    "cname": "天台山",
    "suggest_places": [
      {
        "cname": "琼台仙谷",
        "url": "/sight/tiantaishan246/9079.html"
      },
      {
        "cname": "龙穿峡景区",
        "url": "/sight/tiantaishan246/135759.html"
      },
      {
        "cname": "国清景区",
        "url": "/sight/tiantaishan246/1410515.html"
      },
      {
        "cname": "华顶国家森林公园",
        "url": "/sight/tiantaishan246/9056.html"
      },
      {
        "cname": "赤城山",
        "url": "/sight/tiantaishan246/9001.html"
      }
    ],
    "url": "/sightlist/tiantaishan246.html"
  },
  {
    "cname": "余姚",
    "suggest_places": [
      {
        "cname": "丹山赤水",
        "url": "/sight/yuyao98/23096.html"
      },
      {
        "cname": "天下玉苑",
        "url": "/sight/yuyao98/50596.html"
      },
      {
        "cname": "河姆渡遗址博物馆",
        "url": "/sight/yuyao98/10251.html"
      },
      {
        "cname": "浙东小九寨",
        "url": "/sight/yuyao98/1409499.html"
      },
      {
        "cname": "四明湖",
        "url": "/sight/yuyao98/10118.html"
      }
    ],
    "url": "/sightlist/yuyao98.html"
  },
  {
    "cname": "泰顺",
    "suggest_places": [
      {
        "cname": "北涧桥",
        "url": "/sight/taishun625/20556.html"
      },
      {
        "cname": "三条桥",
        "url": "/sight/taishun625/20538.html"
      },
      {
        "cname": "仙居桥",
        "url": "/sight/taishun625/18280.html"
      },
      {
        "cname": "溪东桥",
        "url": "/sight/taishun625/20553.html"
      },
      {
        "cname": "文兴桥",
        "url": "/sight/taishun625/20557.html"
      }
    ],
    "url": "/sightlist/taishun625.html"
  },
  {
    "cname": "义乌",
    "suggest_places": [
      {
        "cname": "异国风情街",
        "url": "/sight/yiwu1005/57658.html"
      },
      {
        "cname": "稠州公园",
        "url": "/sight/yiwu1005/57696.html"
      },
      {
        "cname": "奇趣海洋世界",
        "url": "/sight/yiwu1005/135701.html"
      },
      {
        "cname": "德胜岩",
        "url": "/sight/yiwu1005/57727.html"
      },
      {
        "cname": "佛堂古镇",
        "url": "/sight/yiwu1005/61020.html"
      }
    ],
    "url": "/sightlist/yiwu1005.html"
  },
  {
    "cname": "嘉善",
    "suggest_places": [
      {
        "cname": "西塘风景区",
        "url": "/sight/jiashan1019/17884.html"
      },
      {
        "cname": "烟雨长廊",
        "url": "/sight/jiashan1019/2094.html"
      },
      {
        "cname": "送子来凤桥",
        "url": "/sight/jiashan1019/2098.html"
      },
      {
        "cname": "石皮弄",
        "url": "/sight/jiashan1019/2100.html"
      },
      {
        "cname": "环秀桥",
        "url": "/sight/jiashan1019/7128.html"
      }
    ],
    "url": "/sightlist/jiashan1019.html"
  },
  {
    "cname": "遂昌",
    "suggest_places": [
      {
        "cname": "南尖岩景区",
        "url": "/sight/suichang1431/74075.html"
      },
      {
        "cname": "遂昌金矿国家矿山公园",
        "url": "/sight/suichang1431/56269.html"
      },
      {
        "cname": "神龙谷",
        "url": "/sight/suichang1431/74211.html"
      },
      {
        "cname": "千佛山景区",
        "url": "/sight/suichang1431/135834.html"
      },
      {
        "cname": "中国竹炭博物馆",
        "url": "/sight/suichang1431/74263.html"
      }
    ],
    "url": "/sightlist/suichang1431.html"
  },
  {
    "cname": "新昌",
    "suggest_places": [
      {
        "cname": "大佛寺景区",
        "url": "/sight/xinchang75/3960.html"
      },
      {
        "cname": "穿岩十九峰",
        "url": "/sight/xinchang75/3967.html"
      },
      {
        "cname": "千丈幽谷",
        "url": "/sight/xinchang75/57611.html"
      },
      {
        "cname": "七盘仙谷",
        "url": "/sight/xinchang75/135885.html"
      },
      {
        "cname": "重阳宫风景区",
        "url": "/sight/xinchang75/141350.html"
      }
    ],
    "url": "/sightlist/xinchang75.html"
  },
  {
    "cname": "诸暨",
    "suggest_places": [
      {
        "cname": "五泄景区",
        "url": "/sight/zhuji690/70738.html"
      },
      {
        "cname": "西施故里",
        "url": "/sight/zhuji690/70744.html"
      },
      {
        "cname": "西施殿",
        "url": "/sight/zhuji690/118117.html"
      },
      {
        "cname": "斗岩风景区",
        "url": "/sight/zhuji690/70746.html"
      },
      {
        "cname": "汤江岩风景区",
        "url": "/sight/zhuji690/110292.html"
      }
    ],
    "url": "/sightlist/zhuji690.html"
  },
  {
    "cname": "宁海",
    "suggest_places": [
      {
        "cname": "前童古镇",
        "url": "/sight/ninghai689/72628.html"
      },
      {
        "cname": "浙东大峡谷",
        "url": "/sight/ninghai689/135809.html"
      },
      {
        "cname": "宁海",
        "url": "/sight/ninghai689/48527.html"
      },
      {
        "cname": "聪明山水景区",
        "url": "/sight/ninghai689/143354.html"
      },
      {
        "cname": "梁皇山景区",
        "url": "/sight/ninghai689/72631.html"
      }
    ],
    "url": "/sightlist/ninghai689.html"
  },
  {
    "cname": "桐庐",
    "suggest_places": [
      {
        "cname": "瑶琳仙境",
        "url": "/sight/tonglu688/49119.html"
      },
      {
        "cname": "严子陵钓台",
        "url": "/sight/tonglu688/49188.html"
      },
      {
        "cname": "大奇山国家森林公园",
        "url": "/sight/tonglu688/49155.html"
      },
      {
        "cname": "垂云通天河景区",
        "url": "/sight/tonglu688/49158.html"
      },
      {
        "cname": "白云源",
        "url": "/sight/tonglu688/49221.html"
      }
    ],
    "url": "/sightlist/tonglu688.html"
  },
  {
    "cname": "兰溪",
    "suggest_places": [
      {
        "cname": "诸葛八卦村",
        "url": "/sight/lanxi611/72172.html"
      },
      {
        "cname": "地下长河景区",
        "url": "/sight/lanxi611/72174.html"
      },
      {
        "cname": "长乐福地",
        "url": "/sight/lanxi611/135904.html"
      },
      {
        "cname": "钟池",
        "url": "/sight/lanxi611/110055.html"
      },
      {
        "cname": "芥子园",
        "url": "/sight/lanxi611/72194.html"
      }
    ],
    "url": "/sightlist/lanxi611.html"
  },
  {
    "cname": "桐乡",
    "suggest_places": [
      {
        "cname": "乌镇",
        "url": "/sight/tongxiang220/16170.html"
      },
      {
        "cname": "西栅",
        "url": "/sight/tongxiang220/139898.html"
      },
      {
        "cname": "东栅",
        "url": "/sight/tongxiang220/139826.html"
      },
      {
        "cname": "西栅夜游",
        "url": "/sight/tongxiang220/135954.html"
      },
      {
        "cname": "茅盾故居",
        "url": "/sight/tongxiang220/18054.html"
      }
    ],
    "url": "/sightlist/tongxiang220.html"
  },
  {
    "cname": "临海",
    "suggest_places": [
      {
        "cname": "江南长城",
        "url": "/sight/linhai544/16913.html"
      },
      {
        "cname": "紫阳街",
        "url": "/sight/linhai544/132783.html"
      },
      {
        "cname": "桃江十三渚",
        "url": "/sight/linhai544/141440.html"
      },
      {
        "cname": "括苍山",
        "url": "/sight/linhai544/16207.html"
      },
      {
        "cname": "东湖",
        "url": "/sight/linhai544/62848.html"
      }
    ],
    "url": "/sightlist/linhai544.html"
  },
  {
    "cname": "东阳",
    "suggest_places": [
      {
        "cname": "横店影视城",
        "url": "/sight/dongyang608/75555.html"
      },
      {
        "cname": "秦王宫景区",
        "url": "/sight/dongyang608/74877.html"
      },
      {
        "cname": "梦幻谷景区",
        "url": "/sight/dongyang608/75559.html"
      },
      {
        "cname": "明清宫苑景区",
        "url": "/sight/dongyang608/135774.html"
      },
      {
        "cname": "广州街香港街",
        "url": "/sight/dongyang608/75563.html"
      }
    ],
    "url": "/sightlist/dongyang608.html"
  },
  {
    "cname": "慈溪",
    "suggest_places": [
      {
        "cname": "达蓬山旅游度假区",
        "url": "/sight/cixi543/20525.html"
      },
      {
        "cname": "杭州湾跨海大桥",
        "url": "/sight/cixi543/55774.html"
      },
      {
        "cname": "大桥生态农庄",
        "url": "/sight/cixi543/50595.html"
      },
      {
        "cname": "海天一洲",
        "url": "/sight/cixi543/135670.html"
      },
      {
        "cname": "慈溪五磊山景区",
        "url": "/sight/cixi543/135676.html"
      }
    ],
    "url": "/sightlist/cixi543.html"
  },
  {
    "cname": "奉化",
    "suggest_places": [
      {
        "cname": "溪口风景区",
        "url": "/sight/fenghua1020/135869.html"
      },
      {
        "cname": "雪窦山",
        "url": "/sight/fenghua1020/107387.html"
      },
      {
        "cname": "雪窦寺",
        "url": "/sight/fenghua1020/4025.html"
      },
      {
        "cname": "三隐潭",
        "url": "/sight/fenghua1020/66245.html"
      },
      {
        "cname": "滕头生态旅游区",
        "url": "/sight/fenghua1020/135857.html"
      }
    ],
    "url": "/sightlist/fenghua1020.html"
  },
  {
    "cname": "大明山",
    "suggest_places": [
      {
        "cname": "大明山风景区",
        "url": "/sight/damingshan120550/4140.html"
      },
      {
        "cname": "飞来峰",
        "url": "/sight/damingshan120550/134627.html"
      },
      {
        "cname": "大明湖",
        "url": "/sight/damingshan120550/134583.html"
      },
      {
        "cname": "悬空栈道",
        "url": "/sight/damingshan120550/134580.html"
      },
      {
        "cname": "明妃七峰",
        "url": "/sight/damingshan120550/134599.html"
      }
    ],
    "url": "/sightlist/damingshan120550.html"
  },
  {
    "cname": "江山",
    "suggest_places": [
      {
        "cname": "廿八都",
        "url": "/sight/jiangshan1000/16771.html"
      },
      {
        "cname": "江郎山景区",
        "url": "/sight/jiangshan1000/16223.html"
      },
      {
        "cname": "浮盖山",
        "url": "/sight/jiangshan1000/139839.html"
      },
      {
        "cname": "清漾毛氏文化村",
        "url": "/sight/jiangshan1000/139875.html"
      },
      {
        "cname": "仙霞关戴笠故居",
        "url": "/sight/jiangshan1000/16225.html"
      }
    ],
    "url": "/sightlist/jiangshan1000.html"
  },
  {
    "cname": "富阳",
    "suggest_places": [
      {
        "cname": "龙门古镇",
        "url": "/sight/fuyang1513/49721.html"
      },
      {
        "cname": "富春桃源",
        "url": "/sight/fuyang1513/49224.html"
      },
      {
        "cname": "富阳",
        "url": "/sight/fuyang1513/49866.html"
      },
      {
        "cname": "新沙岛旅游度假区",
        "url": "/sight/fuyang1513/135887.html"
      },
      {
        "cname": "黄公望隐居地",
        "url": "/sight/fuyang1513/140699.html"
      }
    ],
    "url": "/sightlist/fuyang1513.html"
  },
  {
    "cname": "建德",
    "suggest_places": [
      {
        "cname": "大慈岩风景区",
        "url": "/sight/jiande687/49761.html"
      },
      {
        "cname": "灵栖洞",
        "url": "/sight/jiande687/49790.html"
      },
      {
        "cname": "新叶古村",
        "url": "/sight/jiande687/135928.html"
      },
      {
        "cname": "新安江水电站",
        "url": "/sight/jiande687/49795.html"
      },
      {
        "cname": "千岛湖好运岛",
        "url": "/sight/jiande687/135830.html"
      }
    ],
    "url": "/sightlist/jiande687.html"
  },
  {
    "cname": "东极岛",
    "suggest_places": [
      {
        "cname": "东极岛风景区",
        "url": "/sight/dongjidao120416/57298.html"
      },
      {
        "cname": "庙子湖岛",
        "url": "/sight/dongjidao120416/132078.html"
      },
      {
        "cname": "东福山岛",
        "url": "/sight/dongjidao120416/126049.html"
      },
      {
        "cname": "青浜岛",
        "url": "/sight/dongjidao120416/126048.html"
      },
      {
        "cname": "黄兴岛",
        "url": "/sight/dongjidao120416/132788.html"
      }
    ],
    "url": "/sightlist/dongjidao120416.html"
  },
  {
    "cname": "温岭",
    "suggest_places": [
      {
        "cname": "长屿硐天",
        "url": "/sight/wenling546/16920.html"
      },
      {
        "cname": "石塘",
        "url": "/sight/wenling546/16210.html"
      },
      {
        "cname": "温岭水云硐",
        "url": "/sight/wenling546/141468.html"
      },
      {
        "cname": "观夕洞",
        "url": "/sight/wenling546/62879.html"
      },
      {
        "cname": "方山南嵩岩风景区",
        "url": "/sight/wenling546/16929.html"
      }
    ],
    "url": "/sightlist/wenling546.html"
  },
  {
    "cname": "仙居",
    "suggest_places": [
      {
        "cname": "神仙居",
        "url": "/sight/xianju691/16209.html"
      },
      {
        "cname": "景星岩",
        "url": "/sight/xianju691/135873.html"
      },
      {
        "cname": "皤滩古镇",
        "url": "/sight/xianju691/16921.html"
      },
      {
        "cname": "仙居风景名胜区",
        "url": "/sight/xianju691/62857.html"
      },
      {
        "cname": "高迁古民居",
        "url": "/sight/xianju691/62878.html"
      }
    ],
    "url": "/sightlist/xianju691.html"
  },
  {
    "cname": "萧山",
    "suggest_places": [
      {
        "cname": "湘湖",
        "url": "/sight/xiaoshan120060/47184.html"
      },
      {
        "cname": "杭州极地海洋公园",
        "url": "/sight/xiaoshan120060/110080.html"
      },
      {
        "cname": "萧山",
        "url": "/sight/xiaoshan120060/66790.html"
      },
      {
        "cname": "杭州东方文化园",
        "url": "/sight/xiaoshan120060/135702.html"
      },
      {
        "cname": "杭州浪浪浪水公园",
        "url": "/sight/xiaoshan120060/1411106.html"
      }
    ],
    "url": "/sightlist/xiaoshan120060.html"
  },
  {
    "cname": "开化",
    "suggest_places": [
      {
        "cname": "根宫佛国文化旅游区",
        "url": "/sight/kaihua1001/143278.html"
      },
      {
        "cname": "钱江源国家森林公园",
        "url": "/sight/kaihua1001/135778.html"
      },
      {
        "cname": "古田山自然保护区",
        "url": "/sight/kaihua1001/16772.html"
      }
    ],
    "url": "/sightlist/kaihua1001.html"
  },
  {
    "cname": "余杭",
    "suggest_places": [
      {
        "cname": "塘栖古镇",
        "url": "/sight/yuhang1429/135918.html"
      },
      {
        "cname": "山沟沟景区",
        "url": "/sight/yuhang1429/25557.html"
      },
      {
        "cname": "超山风景区",
        "url": "/sight/yuhang1429/135666.html"
      },
      {
        "cname": "双溪漂流景区",
        "url": "/sight/yuhang1429/135789.html"
      },
      {
        "cname": "余杭",
        "url": "/sight/yuhang1429/66742.html"
      }
    ],
    "url": "/sightlist/yuhang1429.html"
  },
  {
    "cname": "嵊州",
    "suggest_places": [
      {
        "cname": "崇仁古镇",
        "url": "/sight/shengzhou553/20725.html"
      },
      {
        "cname": "嵊州",
        "url": "/sight/shengzhou553/48462.html"
      },
      {
        "cname": "百丈飞瀑",
        "url": "/sight/shengzhou553/21583.html"
      },
      {
        "cname": "王羲之故居旅游区",
        "url": "/sight/shengzhou553/21595.html"
      },
      {
        "cname": "嵊州城隍庙",
        "url": "/sight/shengzhou553/2199.html"
      }
    ],
    "url": "/sightlist/shengzhou553.html"
  },
  {
    "cname": "瑞安",
    "suggest_places": [
      {
        "cname": "花岩国家森林公园",
        "url": "/sight/ruian535/107369.html"
      },
      {
        "cname": "寨寮溪",
        "url": "/sight/ruian535/16192.html"
      },
      {
        "cname": "瑞安外滩",
        "url": "/sight/ruian535/107366.html"
      },
      {
        "cname": "玉海楼",
        "url": "/sight/ruian535/61792.html"
      },
      {
        "cname": "桐溪风景名胜区",
        "url": "/sight/ruian535/61816.html"
      }
    ],
    "url": "/sightlist/ruian535.html"
  },
  {
    "cname": "淳安",
    "suggest_places": [
      {
        "cname": "鸟岛",
        "url": "/sight/chunan2249/143590.html"
      },
      {
        "cname": "千岛湖农夫山泉生产基地",
        "url": "/sight/chunan2249/143588.html"
      }
    ],
    "url": "/sightlist/chunan2249.html"
  },
  {
    "cname": "永嘉",
    "suggest_places": [
      {
        "cname": "石桅岩",
        "url": "/sight/yongjia785/3900.html"
      },
      {
        "cname": "楠溪江风景旅游区",
        "url": "/sight/yongjia785/56450.html"
      },
      {
        "cname": "崖下库",
        "url": "/sight/yongjia785/3897.html"
      },
      {
        "cname": "林坑",
        "url": "/sight/yongjia785/20427.html"
      },
      {
        "cname": "龙湾潭国家森林公园",
        "url": "/sight/yongjia785/46434.html"
      }
    ],
    "url": "/sightlist/yongjia785.html"
  },
  {
    "cname": "沈家门",
    "suggest_places": [
      {
        "cname": "沈家门渔港",
        "url": "/sight/shenjiamen120124/16172.html"
      },
      {
        "cname": "滨港路",
        "url": "/sight/shenjiamen120124/132785.html"
      },
      {
        "cname": "普陀博物馆",
        "url": "/sight/shenjiamen120124/132807.html"
      },
      {
        "cname": "青龙山公园",
        "url": "/sight/shenjiamen120124/132786.html"
      },
      {
        "cname": "鲁家峙岛",
        "url": "/sight/shenjiamen120124/132787.html"
      }
    ],
    "url": "/sightlist/shenjiamen120124.html"
  },
  {
    "cname": "上虞",
    "suggest_places": [
      {
        "cname": "曹娥庙",
        "url": "/sight/shangyu617/74389.html"
      },
      {
        "cname": "桃花源生态旅游区",
        "url": "/sight/shangyu617/74417.html"
      },
      {
        "cname": "东山湖景区",
        "url": "/sight/shangyu617/135883.html"
      },
      {
        "cname": "覆卮山景区",
        "url": "/sight/shangyu617/118463.html"
      },
      {
        "cname": "英台故里祝家庄",
        "url": "/sight/shangyu617/74429.html"
      }
    ],
    "url": "/sightlist/shangyu617.html"
  },
  {
    "cname": "岱山",
    "suggest_places": [
      {
        "cname": "秀山岛景区",
        "url": "/sight/daishan999/24712.html"
      },
      {
        "cname": "鹿栏晴沙景区",
        "url": "/sight/daishan999/57306.html"
      },
      {
        "cname": "磨心山景区",
        "url": "/sight/daishan999/57301.html"
      },
      {
        "cname": "双合石壁",
        "url": "/sight/daishan999/70288.html"
      },
      {
        "cname": "东沙古镇",
        "url": "/sight/daishan999/126126.html"
      }
    ],
    "url": "/sightlist/daishan999.html"
  },
  {
    "cname": "平湖",
    "suggest_places": [
      {
        "cname": "东湖景区",
        "url": "/sight/pinghu533/117845.html"
      },
      {
        "cname": "莫氏庄园",
        "url": "/sight/pinghu533/16168.html"
      },
      {
        "cname": "九龙山旅游度假区",
        "url": "/sight/pinghu533/16169.html"
      },
      {
        "cname": "九龙山国家森林公园",
        "url": "/sight/pinghu533/135737.html"
      },
      {
        "cname": "南湾炮台",
        "url": "/sight/pinghu533/117991.html"
      }
    ],
    "url": "/sightlist/pinghu533.html"
  },
  {
    "cname": "海盐",
    "suggest_places": [
      {
        "cname": "南北湖",
        "url": "/sight/haiyan529/16166.html"
      },
      {
        "cname": "绮园景区",
        "url": "/sight/haiyan529/16688.html"
      },
      {
        "cname": "杭州湾跨海大桥",
        "url": "/sight/haiyan529/56415.html"
      },
      {
        "cname": "谈仙石城",
        "url": "/sight/haiyan529/55842.html"
      },
      {
        "cname": "云岫庵",
        "url": "/sight/haiyan529/55845.html"
      }
    ],
    "url": "/sightlist/haiyan529.html"
  },
  {
    "cname": "乐清",
    "suggest_places": [
      {
        "cname": "中雁荡山",
        "url": "/sight/yueqing1022/135818.html"
      },
      {
        "cname": "杨八洞",
        "url": "/sight/yueqing1022/8386.html"
      },
      {
        "cname": "东祭",
        "url": "/sight/yueqing1022/8388.html"
      },
      {
        "cname": "西祭",
        "url": "/sight/yueqing1022/8387.html"
      },
      {
        "cname": "凤凰山",
        "url": "/sight/yueqing1022/8390.html"
      }
    ],
    "url": "/sightlist/yueqing1022.html"
  },
  {
    "cname": "龙泉",
    "suggest_places": [
      {
        "cname": "龙泉山",
        "url": "/sight/longquan2033/45654.html"
      },
      {
        "cname": "中国青瓷小镇·披云青瓷文化园",
        "url": "/sight/longquan2033/70137.html"
      },
      {
        "cname": "安仁永和桥",
        "url": "/sight/longquan2033/17299.html"
      },
      {
        "cname": "龙泉青瓷博物馆",
        "url": "/sight/longquan2033/1414277.html"
      },
      {
        "cname": "白云岩",
        "url": "/sight/longquan2033/135623.html"
      }
    ],
    "url": "/sightlist/longquan2033.html"
  },
  {
    "cname": "浦江",
    "suggest_places": [
      {
        "cname": "仙华山",
        "url": "/sight/pujiang1002/45180.html"
      },
      {
        "cname": "江南第一家",
        "url": "/sight/pujiang1002/54538.html"
      },
      {
        "cname": "白石湾景区",
        "url": "/sight/pujiang1002/56203.html"
      },
      {
        "cname": "神丽峡",
        "url": "/sight/pujiang1002/45199.html"
      },
      {
        "cname": "官岩山",
        "url": "/sight/pujiang1002/143614.html"
      }
    ],
    "url": "/sightlist/pujiang1002.html"
  },
  {
    "cname": "长兴",
    "suggest_places": [
      {
        "cname": "仙山湖风景区",
        "url": "/sight/changxing1832/56974.html"
      },
      {
        "cname": "金钉子远古世界景区",
        "url": "/sight/changxing1832/135731.html"
      },
      {
        "cname": "中国扬子鳄村",
        "url": "/sight/changxing1832/16759.html"
      },
      {
        "cname": "大唐贡茶院",
        "url": "/sight/changxing1832/56978.html"
      },
      {
        "cname": "古银杏长廊",
        "url": "/sight/changxing1832/56970.html"
      }
    ],
    "url": "/sightlist/changxing1832.html"
  },
  {
    "cname": "洞头",
    "suggest_places": [
      {
        "cname": "望海楼",
        "url": "/sight/dongtou506/67355.html"
      },
      {
        "cname": "仙叠岩",
        "url": "/sight/dongtou506/16198.html"
      },
      {
        "cname": "大沙岙",
        "url": "/sight/dongtou506/9146.html"
      },
      {
        "cname": "半屏山",
        "url": "/sight/dongtou506/9150.html"
      },
      {
        "cname": "大瞿岛",
        "url": "/sight/dongtou506/9174.html"
      }
    ],
    "url": "/sightlist/dongtou506.html"
  },
  {
    "cname": "桃花岛",
    "suggest_places": [
      {
        "cname": "桃花岛风景区",
        "url": "/sight/taohuadao120435/57286.html"
      },
      {
        "cname": "桃花峪景区",
        "url": "/sight/taohuadao120435/57290.html"
      },
      {
        "cname": "桃花寨",
        "url": "/sight/taohuadao120435/126161.html"
      },
      {
        "cname": "塔湾金沙景区",
        "url": "/sight/taohuadao120435/16179.html"
      },
      {
        "cname": "大佛岩景区",
        "url": "/sight/taohuadao120435/16175.html"
      }
    ],
    "url": "/sightlist/taohuadao120435.html"
  },
  {
    "cname": "永康",
    "suggest_places": [
      {
        "cname": "方岩风景名胜区",
        "url": "/sight/yongkang189/17286.html"
      },
      {
        "cname": "岩下老街",
        "url": "/sight/yongkang189/1417183.html"
      },
      {
        "cname": "五峰景区",
        "url": "/sight/yongkang189/141056.html"
      },
      {
        "cname": "白云风景区",
        "url": "/sight/yongkang189/141054.html"
      },
      {
        "cname": "石鼓寮风景区",
        "url": "/sight/yongkang189/56206.html"
      }
    ],
    "url": "/sightlist/yongkang189.html"
  },
  {
    "cname": "磐安",
    "suggest_places": [
      {
        "cname": "十八涡景区",
        "url": "/sight/panan2028/56204.html"
      },
      {
        "cname": "花溪风景区",
        "url": "/sight/panan2028/56197.html"
      },
      {
        "cname": "磐安水下孔景区",
        "url": "/sight/panan2028/140713.html"
      },
      {
        "cname": "灵江源漂流",
        "url": "/sight/panan2028/135752.html"
      },
      {
        "cname": "玉山古茶场",
        "url": "/sight/panan2028/144290.html"
      }
    ],
    "url": "/sightlist/panan2028.html"
  },
  {
    "cname": "云和",
    "suggest_places": [
      {
        "cname": "云和梯田景区",
        "url": "/sight/yunhe2251/135977.html"
      },
      {
        "cname": "云和湖仙宫景区",
        "url": "/sight/yunhe2251/135983.html"
      },
      {
        "cname": "儿童第三空间",
        "url": "/sight/yunhe2251/1415621.html"
      },
      {
        "cname": "王一卿墓",
        "url": "/sight/yunhe2251/143621.html"
      },
      {
        "cname": "玩具智慧园",
        "url": "/sight/yunhe2251/70312.html"
      }
    ],
    "url": "/sightlist/yunhe2251.html"
  },
  {
    "cname": "缙云",
    "suggest_places": [
      {
        "cname": "仙都风景名胜区",
        "url": "/sight/jinyun1021/135870.html"
      },
      {
        "cname": "仙都景区",
        "url": "/sight/jinyun1021/56295.html"
      },
      {
        "cname": "小赤壁",
        "url": "/sight/jinyun1021/8466.html"
      },
      {
        "cname": "河阳古民居",
        "url": "/sight/jinyun1021/56346.html"
      },
      {
        "cname": "袁枚《游仙都峰记》刻石",
        "url": "/sight/jinyun1021/56312.html"
      }
    ],
    "url": "/sightlist/jinyun1021.html"
  },
  {
    "cname": "青田",
    "suggest_places": [
      {
        "cname": "石门洞 ",
        "url": "/sight/qingtian2247/16215.html"
      },
      {
        "cname": "千丝岩石文化公园",
        "url": "/sight/qingtian2247/17308.html"
      },
      {
        "cname": "中国田鱼村",
        "url": "/sight/qingtian2247/143564.html"
      },
      {
        "cname": "中国青田石雕文化旅游区",
        "url": "/sight/qingtian2247/69587.html"
      },
      {
        "cname": "陈诚故居",
        "url": "/sight/qingtian2247/143566.html"
      }
    ],
    "url": "/sightlist/qingtian2247.html"
  },
  {
    "cname": "诸葛八卦村",
    "suggest_places": [
      {
        "cname": "诸葛八卦村",
        "url": "/sight/zhugebaguavillage120100/72172.html"
      },
      {
        "cname": "钟池",
        "url": "/sight/zhugebaguavillage120100/110055.html"
      },
      {
        "cname": "丞相祠堂",
        "url": "/sight/zhugebaguavillage120100/110054.html"
      },
      {
        "cname": "天一堂",
        "url": "/sight/zhugebaguavillage120100/110056.html"
      },
      {
        "cname": "大公堂",
        "url": "/sight/zhugebaguavillage120100/110053.html"
      }
    ],
    "url": "/sightlist/zhugebaguavillage120100.html"
  },
  {
    "cname": "龙游",
    "suggest_places": [
      {
        "cname": "龙游石窟",
        "url": "/sight/longyou812/16766.html"
      },
      {
        "cname": "龙游民居苑",
        "url": "/sight/longyou812/16768.html"
      },
      {
        "cname": "衢州小南海",
        "url": "/sight/longyou812/16767.html"
      }
    ],
    "url": "/sightlist/longyou812.html"
  },
  {
    "cname": "平阳",
    "suggest_places": [
      {
        "cname": "南雁荡山",
        "url": "/sight/pingyang1012/110077.html"
      },
      {
        "cname": "三盘尾",
        "url": "/sight/pingyang1012/9176.html"
      },
      {
        "cname": "云祥寺",
        "url": "/sight/pingyang1012/8486.html"
      },
      {
        "cname": "南麂山列岛",
        "url": "/sight/pingyang1012/135806.html"
      },
      {
        "cname": "东南屏障",
        "url": "/sight/pingyang1012/16896.html"
      }
    ],
    "url": "/sightlist/pingyang1012.html"
  },
  {
    "cname": "镇海",
    "suggest_places": [
      {
        "cname": "九龙湖景区",
        "url": "/sight/zhenhai143873/67857.html"
      },
      {
        "cname": "招宝山",
        "url": "/sight/zhenhai143873/45093.html"
      },
      {
        "cname": "郑氏十七房",
        "url": "/sight/zhenhai143873/117312.html"
      },
      {
        "cname": "宝陀禅寺",
        "url": "/sight/zhenhai143873/1481142.html"
      },
      {
        "cname": "镇海口海防遗址",
        "url": "/sight/zhenhai143873/9952.html"
      }
    ],
    "url": "/sightlist/zhenhai143873.html"
  },
  {
    "cname": "文成",
    "suggest_places": [
      {
        "cname": "铜铃山森林公园",
        "url": "/sight/wencheng1003/50598.html"
      },
      {
        "cname": "九九桥",
        "url": "/sight/wencheng1003/1487932.html"
      },
      {
        "cname": "观稼亭",
        "url": "/sight/wencheng1003/1487952.html"
      },
      {
        "cname": "武阳古村",
        "url": "/sight/wencheng1003/1493419.html"
      },
      {
        "cname": "刘基故里",
        "url": "/sight/wencheng1003/9172.html"
      }
    ],
    "url": "/sightlist/wencheng1003.html"
  },
  {
    "cname": "慈城镇",
    "suggest_places": [
      {
        "cname": "慈城古县城",
        "url": "/sight/cichengtown120095/139824.html"
      },
      {
        "cname": "慈城孔庙",
        "url": "/sight/cichengtown120095/1479039.html"
      },
      {
        "cname": "慈城校士馆",
        "url": "/sight/cichengtown120095/1479382.html"
      },
      {
        "cname": "慈城县衙",
        "url": "/sight/cichengtown120095/1478997.html"
      },
      {
        "cname": "妙音庵",
        "url": "/sight/cichengtown120095/1479966.html"
      }
    ],
    "url": "/sightlist/cichengtown120095.html"
  },
  {
    "cname": "庆元",
    "suggest_places": [
      {
        "cname": "百山祖景区",
        "url": "/sight/qingyuan2248/17297.html"
      },
      {
        "cname": "月山村",
        "url": "/sight/qingyuan2248/45695.html"
      },
      {
        "cname": "兰溪桥",
        "url": "/sight/qingyuan2248/56133.html"
      },
      {
        "cname": "如龙桥",
        "url": "/sight/qingyuan2248/45677.html"
      },
      {
        "cname": "庆元古桥",
        "url": "/sight/qingyuan2248/56193.html"
      }
    ],
    "url": "/sightlist/qingyuan2248.html"
  },
  {
    "cname": "三门",
    "suggest_places": [
      {
        "cname": "蛇蟠岛",
        "url": "/sight/sanmen1945/16206.html"
      },
      {
        "cname": "蛇蟠岛海盗村",
        "url": "/sight/sanmen1945/144048.html"
      },
      {
        "cname": "石笋山",
        "url": "/sight/sanmen1945/1488761.html"
      },
      {
        "cname": "东屏古村",
        "url": "/sight/sanmen1945/144168.html"
      },
      {
        "cname": "蛇蟠岛野人洞",
        "url": "/sight/sanmen1945/144389.html"
      }
    ],
    "url": "/sightlist/sanmen1945.html"
  },
  {
    "cname": "景宁",
    "suggest_places": [
      {
        "cname": "云中大漈",
        "url": "/sight/jingning2034/17303.html"
      },
      {
        "cname": "畲乡之窗",
        "url": "/sight/jingning2034/17304.html"
      },
      {
        "cname": "东弄村",
        "url": "/sight/jingning2034/143949.html"
      },
      {
        "cname": "双后岗畲族文化村",
        "url": "/sight/jingning2034/16216.html"
      },
      {
        "cname": "大均古街",
        "url": "/sight/jingning2034/143613.html"
      }
    ],
    "url": "/sightlist/jingning2034.html"
  },
  {
    "cname": "松阳",
    "suggest_places": [
      {
        "cname": "箬寮原始林",
        "url": "/sight/songyang2250/45731.html"
      },
      {
        "cname": "延庆寺塔",
        "url": "/sight/songyang2250/45734.html"
      },
      {
        "cname": "石仓清代民居群",
        "url": "/sight/songyang2250/45735.html"
      },
      {
        "cname": "寨头摄影休闲园",
        "url": "/sight/songyang2250/144266.html"
      },
      {
        "cname": "包杰进士牌坊",
        "url": "/sight/songyang2250/1511146.html"
      }
    ],
    "url": "/sightlist/songyang2250.html"
  },
  {
    "cname": "玉环",
    "suggest_places": [
      {
        "cname": "大鹿岛",
        "url": "/sight/yuhuan1006/16211.html"
      },
      {
        "cname": "玉环漩门湾湿地公园",
        "url": "/sight/yuhuan1006/1675508.html"
      },
      {
        "cname": "白马岙",
        "url": "/sight/yuhuan1006/143907.html"
      }
    ],
    "url": "/sightlist/yuhuan1006.html"
  },
  {
    "cname": "苍南",
    "suggest_places": [
      {
        "cname": "赤溪五洞桥",
        "url": "/sight/cangnan2049/144150.html"
      },
      {
        "cname": "余家大院",
        "url": "/sight/cangnan2049/1508908.html"
      },
      {
        "cname": "渔寮风景区",
        "url": "/sight/cangnan2049/50597.html"
      },
      {
        "cname": "洗马桥",
        "url": "/sight/cangnan2049/1508902.html"
      },
      {
        "cname": "仙堂山遗址",
        "url": "/sight/cangnan2049/143628.html"
      }
    ],
    "url": "/sightlist/cangnan2049.html"
  },
  {
    "cname": "六横岛",
    "suggest_places": [
      {
        "cname": "黄荆寺",
        "url": "/sight/liuhengdao120437/132799.html"
      },
      {
        "cname": "六横岛",
        "url": "/sight/liuhengdao120437/57311.html"
      },
      {
        "cname": "普陀假日岛",
        "url": "/sight/liuhengdao120437/132797.html"
      },
      {
        "cname": "东总英烈纪念园 ",
        "url": "/sight/liuhengdao120437/132798.html"
      },
      {
        "cname": "龙头跳",
        "url": "/sight/liuhengdao120437/57319.html"
      }
    ],
    "url": "/sightlist/liuhengdao120437.html"
  }
]
