[
  {
    "cname": "赫尔辛基",
    "url": "http://you.ctrip.com/sightlist/helsinki452.html",
    "places": [
      {
        "cname": "岩石教堂",
        "url": "/sight/helsinki452/25472.html",
        "s_img": "http://p.chanyouji.cn/23311/1359943483671p17ihf5ba11ken1q3e4be1j3132g5.jpg?imageView/1/w/220/h/140",
        "caddress": "Lutherinkatu 3, 00100 Helsinki"
      },
      {
        "cname": "赫尔辛基大教堂",
        "url": "/sight/helsinki452/25474.html",
        "s_img": "http://p.chanyouji.cn/141997/1405085232017p18sipg5u116c91a0p4l97v8t0r2p.jpg?imageView/1/w/220/h/140",
        "caddress": "Unioninkatu 29, 00170 Helsinki, Finland"
      },
      {
        "cname": "赫尔辛基",
        "url": "/sight/helsinki452/139256.html",
        "s_img": "http://dimg02.c-ctrip.com/images/tg/679/005/069/2b117fb7c8ed4ed0aa3cf3d3254b971c_C_220_140.jpg",
        "caddress": ""
      },
      {
        "cname": "西贝柳斯公园",
        "url": "/sight/helsinki452/25479.html",
        "s_img": "http://p.chanyouji.cn/1377601879/E67F20BF-5D76-45C1-96FD-AAC758145B08.jpg?imageView/1/w/220/h/140",
        "caddress": "Sibeliuksen puisto, Mechelininkatu, 00250 Helsinki"
      },
      {
        "cname": "乌斯别斯基东正大教堂",
        "url": "/sight/helsinki452/25475.html",
        "s_img": "http://dimg02.c-ctrip.com/images/tg/629/220/600/721e41009e614e1f8ec3f962529a054d_C_220_140.jpg",
        "caddress": ""
      },
      {
        "cname": "芬兰堡",
        "url": "/sight/helsinki452/25471.html",
        "s_img": "http://p.chanyouji.cn/27436/1362683919042p17l34i1911p0h1qg98gechc1klea.jpg?imageView/1/w/220/h/140",
        "caddress": "Suomenlinna C 74, 00190 Helsinki"
      },
      {
        "cname": "议会大厦",
        "url": "/sight/helsinki452/136597.html",
        "s_img": "http://dimg02.c-ctrip.com/images/tg/764/873/235/73387ba93a5a4ffe8a2bb2e9cbde5714_C_220_140.jpg",
        "caddress": "Mannerheimintie 30, Helsinki, Suomi"
      },
      {
        "cname": "伴侣岛 ",
        "url": "/sight/helsinki452/25469.html",
        "s_img": "http://dimg02.c-ctrip.com/images/tg/605/777/867/48c8af14706d4dcba94af127e2ce6eee_C_220_140.jpg",
        "caddress": "Seurasaari,Helsinki, Finland"
      },
      {
        "cname": "图尔库城堡",
        "url": "/sight/turku1078/67526.html",
        "s_img": "http://dimg02.c-ctrip.com/images/tg/468/342/482/57f9909b20d64be5b51759e2c9f42a17_C_220_140.jpg",
        "caddress": "Linnankatu 80, Turku 20100 , Finland"
      },
      {
        "cname": "议会广场",
        "url": "/sight/helsinki452/25473.html",
        "s_img": "http://dimg02.c-ctrip.com/images/tg/656/836/945/6f7c59df6368409eb47a8ce77ce452cd_C_220_140.jpg",
        "caddress": "Mannerheimintie 30, Helsinki, Finland"
      },
      {
        "cname": "芬兰国家博物馆",
        "url": "/sight/helsinki452/136592.html",
        "s_img": "http://dimg02.c-ctrip.com/images/tg/736/398/290/d264e23bdd1341bcaaf8942e75e48133_C_220_140.jpg",
        "caddress": "Mannerheimintie 34, Helsinki 00101, Finland"
      },
      {
        "cname": "伴侣岛露天博物馆",
        "url": "/sight/helsinki452/136586.html",
        "s_img": "http://dimg02.c-ctrip.com/images/tg/396/619/994/2eedca3ffe214ae380550e30c4850305_C_220_140.jpg",
        "caddress": "Seurasaari, Helsinki, Finland"
      },
      {
        "cname": "赫尔辛基大学主图书馆",
        "url": "/sight/helsinki452/1410656.html",
        "s_img": "http://dimg02.c-ctrip.com/images/tg/974/240/646/3a97597c4300450aa00e483c86a028c5_C_220_140.jpg",
        "caddress": "Fabianinkatu 30, 00014 Helsinki"
      },
      {
        "cname": "波尔沃古城",
        "url": "/sight/helsinki452/1494061.html",
        "s_img": "http://dimg02.c-ctrip.com/images/fd/tg/g1/M0A/A3/1A/CghzflT9DYuASZDvAAIsEQjaQ1o027_C_220_140.jpg",
        "caddress": "FI-06101 Porvoo"
      },
      {
        "cname": "阿曼达铜像",
        "url": "/sight/helsinki452/1409864.html",
        "s_img": "http://dimg02.c-ctrip.com/images/tg/184/842/265/c434f0ccca2e47f2aca0f10572941aef_C_220_140.jpg",
        "caddress": "Kauppatori 00130 Helsinki, Suomi"
      },
      {
        "cname": "波罗的海芬兰湾",
        "url": "/sight/helsinki452/136591.html",
        "s_img": "http://dimg02.c-ctrip.com/images/tg/217/930/335/d27318c6a2ec4868b80a4f324636057a_C_220_140.jpg",
        "caddress": "Gulf of Finland"
      },
      {
        "cname": "奥林匹克公园",
        "url": "/sight/helsinki452/1409861.html",
        "s_img": "http://dimg02.c-ctrip.com/images/tg/072/321/031/f2a316ca149a4665a7ee6c1276d7f172_C_220_140.jpg",
        "caddress": "Paavo Nurmen tie 1, 00250 Helsinki"
      },
      {
        "cname": "当代艺术博物馆(奇亚斯马)",
        "url": "/sight/helsinki452/25476.html",
        "s_img": "http://dimg02.c-ctrip.com/images/tg/830/725/708/8e22f7e882b2430ab5630277c1b2dfbc_C_220_140.jpg",
        "caddress": "Mannerheiminaukio 2, 00100 Helsinki, 芬兰"
      },
      {
        "cname": "艾斯堡",
        "url": "/sight/helsinki452/67523.html",
        "s_img": "http://dimg02.c-ctrip.com/images/tg/604/543/888/7e36cf883e6f4dc69f904f9dd35f30ac_C_220_140.jpg",
        "caddress": "芬兰埃斯波"
      },
      {
        "cname": "奥尔涅米技术大学",
        "url": "/sight/helsinki452/1493456.html",
        "s_img": "",
        "caddress": "Aalto University 02150 Espoo, 芬兰"
      },
      {
        "cname": "比赫拉亚岛",
        "url": "/sight/helsinki452/1494020.html",
        "s_img": "",
        "caddress": "Pihlajasaari island（赫尔辛基境内）"
      },
      {
        "cname": "赫尔辛基议会广场",
        "url": "/sight/helsinki452/1494115.html",
        "s_img": "",
        "caddress": "00170 Helsinki"
      },
      {
        "cname": "努克西奥国家公园",
        "url": "/sight/helsinki452/1494042.html",
        "s_img": "",
        "caddress": "32 ESPOO，Haukkalammentie"
      },
      {
        "cname": "许温凯",
        "url": "/sight/helsinki452/1487931.html",
        "s_img": "",
        "caddress": "05800 Hyvinkää"
      },
      {
        "cname": "芬兰国家美术馆",
        "url": "/sight/helsinki452/25477.html",
        "s_img": "http://dimg02.c-ctrip.com/images/tg/611/908/453/d2ef025bbc2c4dde88257838dc2e9a06_C_220_140.jpg",
        "caddress": ""
      },
      {
        "cname": "芬兰国家图书馆",
        "url": "/sight/helsinki452/1493984.html",
        "s_img": "",
        "caddress": "Fabiansgatan 30, 00014 Helsingfors"
      },
      {
        "cname": "康比教堂",
        "url": "/sight/helsinki452/1493979.html",
        "s_img": "",
        "caddress": "Simonsgatan 7 00100 Helsinki"
      },
      {
        "cname": "乌斯佩斯基大教堂",
        "url": "/sight/helsinki452/1508186.html",
        "s_img": "",
        "caddress": "Kanavakatu 1 00160 Helsinki"
      },
      {
        "cname": "议会大楼",
        "url": "/sight/helsinki452/1508088.html",
        "s_img": "",
        "caddress": "Mannerheimintie 30 00100 Helsinki"
      },
      {
        "cname": "赫尔辛基圣约翰教堂",
        "url": "/sight/helsinki452/1508087.html",
        "s_img": "",
        "caddress": "Helsinki Högbergsgatan"
      },
      {
        "cname": "波尔沃大教堂",
        "url": "/sight/helsinki452/1410072.html",
        "s_img": "http://dimg02.c-ctrip.com/images/tg/417/440/135/294ca0e97b434b2fb99c2d33f0fe0e87_C_220_140.jpg",
        "caddress": "Kyrkotorget 1, 06100 Borgå, Helsinki"
      },
      {
        "cname": "曼纳林博物馆",
        "url": "/sight/helsinki452/74497.html",
        "s_img": "http://dimg02.c-ctrip.com/images/tg/110/692/209/c115bfb83bd146edb9986274573de8f1_C_220_140.jpg",
        "caddress": "Kallionlinnantie 14, Helsinki 00140, Finland"
      },
      {
        "cname": "艾伦怀特博物馆",
        "url": "/sight/helsinki452/1493452.html",
        "s_img": "",
        "caddress": "Suomenlinna B 40 00190 Helsinki"
      },
      {
        "cname": "奥运塔",
        "url": "/sight/helsinki452/1494065.html",
        "s_img": "",
        "caddress": "Paavo Nurmen tie 1 00250 Helsinki"
      },
      {
        "cname": "伯格之屋",
        "url": "/sight/helsinki452/1493441.html",
        "s_img": "",
        "caddress": "Kristianinkatu 12 00170 Helsinki"
      },
      {
        "cname": "芬兰堡博物馆",
        "url": "/sight/helsinki452/1494071.html",
        "s_img": "",
        "caddress": "Halosenniemi Halosenniementie 4-6 04310 Tuusula"
      },
      {
        "cname": "海洋大世界",
        "url": "/sight/helsinki452/1493805.html",
        "s_img": "",
        "caddress": "Tivolitie 10 00510 Helsinki"
      },
      {
        "cname": "赫尔辛基设计博物馆",
        "url": "/sight/helsinki452/1493998.html",
        "s_img": "",
        "caddress": "Högbergsgatan 23 00130 Helsinki"
      },
      {
        "cname": "赫尔辛基音乐中心",
        "url": "/sight/helsinki452/1494056.html",
        "s_img": "",
        "caddress": "Mannerheimintie 13e 00100 Helsinki"
      },
      {
        "cname": "剧院博物馆",
        "url": "/sight/helsinki452/1493957.html",
        "s_img": "",
        "caddress": "1g, Tallberginkatu 00180 Helsinki"
      },
      {
        "cname": "玩具博物馆",
        "url": "/sight/helsinki452/1493991.html",
        "s_img": "",
        "caddress": "Suomenlinna C 66, 00190 Helsinki"
      },
      {
        "cname": "威斯高潜艇博物馆",
        "url": "/sight/helsinki452/1493972.html",
        "s_img": "",
        "caddress": "Suomenlinna 00190 Helsinki"
      },
      {
        "cname": "沃尔特雕像收藏馆",
        "url": "/sight/helsinki452/1493412.html",
        "s_img": "",
        "caddress": "Aleksanterinkatu 5"
      },
      {
        "cname": "总统府",
        "url": "/sight/helsinki452/1494081.html",
        "s_img": "",
        "caddress": "Mariankatu 2 00170 Helsinki"
      },
      {
        "cname": "赫尔辛基中央火车站",
        "url": "/sight/helsinki452/142403.html",
        "s_img": "http://dimg02.c-ctrip.com/images/tg/555/492/603/5d4f9c13dbf34d1a907efafa165e4e1b_C_220_140.jpg",
        "caddress": "Kaivokatu 1"
      },
      {
        "cname": "赫尤里卡科学中心",
        "url": "/sight/helsinki452/1493451.html",
        "s_img": "",
        "caddress": "Kuninkaalantie 7 1300 Vantaa"
      },
      {
        "cname": "Aarikka",
        "url": "/sight/helsinki452/142404.html",
        "s_img": "http://dimg02.c-ctrip.com/images/tg/039/873/813/5fa658e6784345efb67876ded7e396f8_C_220_140.jpg",
        "caddress": "Pohjoisesplanadi 27"
      },
      {
        "cname": "Itakeskuksen Poliklinikka Oy",
        "url": "/sight/helsinki452/142405.html",
        "s_img": "",
        "caddress": "Abohusvagen 4，00930 Helsingfors"
      }
    ]
  },
  {
    "cname": "罗凡涅米",
    "url": "http://you.ctrip.com/sightlist/lapland1049.html",
    "places": [
      {
        "cname": "圣诞老人村",
        "url": "/sight/lapland1049/26568.html",
        "s_img": "http://dimg02.c-ctrip.com/images/fd/tg/g1/M06/61/F9/CghzfFTAtsmAaijoAAk0JaTUrEA446_C_220_140.jpg",
        "caddress": ""
      },
      {
        "cname": "北极圈",
        "url": "/sight/lapland1049/26563.html",
        "s_img": "http://dimg02.c-ctrip.com/images/tg/610/113/941/e63d12b236f34ddda0b5b289372e0232_C_220_140.jpg",
        "caddress": "Rovaniemi, Finland"
      },
      {
        "cname": "圣诞公园",
        "url": "/sight/lapland1049/26569.html",
        "s_img": "http://dimg02.c-ctrip.com/images/tg/738/272/018/95d694f4d6064fa1924db5190eb36fb4_C_220_140.jpg",
        "caddress": "Rovaniemi 96930, Finland"
      },
      {
        "cname": "桑普号破冰船",
        "url": "/sight/lapland1049/26572.html",
        "s_img": "http://dimg02.c-ctrip.com/images/tg/014/759/140/20a956bb55584595a675e0043860a3cb_C_220_140.jpg",
        "caddress": "Sampo Tours - Torikatu 4; Kemi, Finland, Kemi, Finland"
      },
      {
        "cname": "冰雪城堡",
        "url": "/sight/lapland1049/26565.html",
        "s_img": "http://dimg02.c-ctrip.com/images/tg/506/232/877/37dc292eb2274c6ca581d6070a846645_C_220_140.jpg",
        "caddress": "Kauppakatu 29, Kemi, Finland"
      },
      {
        "cname": "萨米博物馆",
        "url": "/sight/lapland1049/26582.html",
        "s_img": "http://dimg02.c-ctrip.com/images/tg/785/888/283/f2cc766b2596426aadf665a2c940c174_C_220_140.jpg",
        "caddress": "Inarintie 46, 99870 Inari"
      },
      {
        "cname": "Pakasaivo",
        "url": "/sight/lapland1049/26584.html",
        "s_img": "",
        "caddress": "Pakasaivo, 95950 穆奥尼奥"
      },
      {
        "cname": "北极中心",
        "url": "/sight/lapland1049/26564.html",
        "s_img": "http://dimg02.c-ctrip.com/images/tg/658/426/760/289e37759c5e40a79fac9d83bddee924_C_220_140.jpg",
        "caddress": "Pohjoisranta 4, 96200 Rovaniemi"
      },
      {
        "cname": "托尔纳河",
        "url": "/sight/lapland1049/26587.html",
        "s_img": "",
        "caddress": "Tornio-Muonio River"
      },
      {
        "cname": "紫水晶矿",
        "url": "/sight/lapland1049/26576.html",
        "s_img": "",
        "caddress": ""
      },
      {
        "cname": "北极光教堂",
        "url": "/sight/lapland1049/26580.html",
        "s_img": "",
        "caddress": "Kappelitie 2, 98530 Pelkosenniemi"
      },
      {
        "cname": "凯米宝石馆",
        "url": "/sight/kemi1076/26571.html",
        "s_img": "http://dimg02.c-ctrip.com/images/tg/048/385/117/a23f493648e4460fb32c0f1ba3ec7dcd_C_220_140.jpg",
        "caddress": ""
      },
      {
        "cname": "罗凡涅米教堂",
        "url": "/sight/lapland1049/26566.html",
        "s_img": "http://dimg02.c-ctrip.com/images/tg/376/044/402/ef7eee2ff4194a9c8ce07ab6cbb69fbe_C_220_140.jpg",
        "caddress": "Rauhankatu 70, Rovaniemi 96101, Finland"
      },
      {
        "cname": "森林博物馆",
        "url": "/sight/lapland1049/26567.html",
        "s_img": "",
        "caddress": "Lustontie 1, Punkaharju 58450 , Finland"
      },
      {
        "cname": "圣洗湖",
        "url": "/sight/lapland1049/26577.html",
        "s_img": "",
        "caddress": "Pyhä-Luosto National Park, 98530 Pelkosenniemi"
      },
      {
        "cname": "雪橇狗公园",
        "url": "/sight/lapland1049/26581.html",
        "s_img": "",
        "caddress": "Parkkitie 5, 98530 Pelkosenniemi"
      },
      {
        "cname": "Ranua野生动物园",
        "url": "/sight/lapland1049/26570.html",
        "s_img": "",
        "caddress": ""
      },
      {
        "cname": "萨利色尔卡金矿",
        "url": "/sight/lapland1049/26583.html",
        "s_img": "http://dimg02.c-ctrip.com/images/tg/529/078/383/ccdec22a7c004cbc983d0dc1d32b8caf_C_220_140.jpg",
        "caddress": ""
      },
      {
        "cname": "洛斯托度假中心",
        "url": "/sight/lapland1049/26575.html",
        "s_img": "",
        "caddress": ""
      },
      {
        "cname": "Kuru剧场",
        "url": "/sight/lapland1049/26578.html",
        "s_img": "",
        "caddress": ""
      }
    ]
  },
  {
    "cname": "图尔库",
    "url": "http://you.ctrip.com/sightlist/turku1078.html",
    "places": [
      {
        "cname": "图尔库城堡",
        "url": "/sight/turku1078/67526.html",
        "s_img": "http://dimg02.c-ctrip.com/images/tg/468/342/482/57f9909b20d64be5b51759e2c9f42a17_C_220_140.jpg",
        "caddress": "Linnankatu 80, Turku 20100 , Finland"
      },
      {
        "cname": "图尔库教堂",
        "url": "/sight/turku1078/136598.html",
        "s_img": "http://dimg02.c-ctrip.com/images/tg/769/411/680/a2c4ef73264b4230a3a9c05dd1b80327_C_220_140.jpg",
        "caddress": "Tuomiokirkkotori 20, Turku 20500, Finland"
      }
    ]
  },
  {
    "cname": "凯米",
    "url": "http://you.ctrip.com/sightlist/kemi1076.html",
    "places": [
      {
        "cname": "凯米宝石馆",
        "url": "/sight/kemi1076/26571.html",
        "s_img": "http://dimg02.c-ctrip.com/images/tg/048/385/117/a23f493648e4460fb32c0f1ba3ec7dcd_C_220_140.jpg",
        "caddress": ""
      }
    ]
  },
  {
    "cname": "Espoo",
    "url": "http://you.ctrip.com/sightlist/espoo45722.html",
    "places": [
      {
        "cname": "努克西奥国家公园",
        "url": "/sight/espoo45722/25470.html",
        "s_img": "http://dimg02.c-ctrip.com/images/tg/571/571/001/eb1d34cfa5134d51a04046b814105c15_C_220_140.jpg",
        "caddress": "Espoo, 芬兰"
      },
      {
        "cname": "诺基亚中心",
        "url": "/sight/espoo45722/136595.html",
        "s_img": "http://dimg02.c-ctrip.com/images/tg/657/063/982/da298bd5027940a488cbd7bf824372c7_C_220_140.jpg",
        "caddress": "Keilalahdentie 4, Espoo, Suomi"
      }
    ]
  },
  {
    "cname": "坦佩雷",
    "url": "http://you.ctrip.com/sightlist/tampere1077.html",
    "places": []
  },
  {
    "cname": "库奥皮奥",
    "url": "http://you.ctrip.com/sightlist/kuopio1419.html",
    "places": [
      {
        "cname": "库奥皮奥博物馆",
        "url": "/sight/kuopio1419/71190.html",
        "s_img": "http://dimg02.c-ctrip.com/images/tg/536/193/552/8e6bc77949514cd5aaac4a1a71e1cc79_C_220_140.jpg",
        "caddress": "Kirkkokatu 22, 70100 Kuopio"
      },
      {
        "cname": "普幽山",
        "url": "/sight/kuopio1419/71192.html",
        "s_img": "http://dimg02.c-ctrip.com/images/tg/698/447/628/0a212c4126494f1685a58d6a6db6ca22_C_220_140.jpg",
        "caddress": "Puijo tower, 70280 Kuopio"
      },
      {
        "cname": "东正教教堂博物馆",
        "url": "/sight/kuopio1419/71191.html",
        "s_img": "http://dimg02.c-ctrip.com/images/tg/192/283/825/03ff3686d36e4810929e6187d6bd5857_C_220_140.jpg",
        "caddress": ""
      }
    ]
  },
  {
    "cname": "奥卢",
    "url": "http://you.ctrip.com/sightlist/oulu1361.html",
    "places": []
  }
]